LICENSE
MANIFEST.in
README.md
pyproject.toml
setup.py
include/msvc9/stdint.h
murmurhash/MurmurHash2.cpp
murmurhash/MurmurHash3.cpp
murmurhash/__init__.pxd
murmurhash/__init__.py
murmurhash/about.py
murmurhash/mrmr.pxd
murmurhash/mrmr.pyx
murmurhash/include/murmurhash/MurmurHash2.h
murmurhash/include/murmurhash/MurmurHash3.h
murmurhash/tests/__init__.py
murmurhash/tests/test_hash.py
murmurhash/tests/test_import.py
murmurhash_lxneng.egg-info/PKG-INFO
murmurhash_lxneng.egg-info/SOURCES.txt
murmurhash_lxneng.egg-info/dependency_links.txt
murmurhash_lxneng.egg-info/not-zip-safe
murmurhash_lxneng.egg-info/top_level.txt